spora/__init__.py
spora/config.py
spora/init_defaults.py
spora/main.py
spora/workflows/spora.smk
spora/workflows/spora_summary_report.Rmd
spora-0.7.0.data/scripts/spora.smk
spora-0.7.0.data/scripts/spora_summary_report.Rmd
spora-0.7.0.dist-info/LICENSE
spora-0.7.0.dist-info/METADATA
spora-0.7.0.dist-info/WHEEL
spora-0.7.0.dist-info/entry_points.txt
spora-0.7.0.dist-info/top_level.txt
spora-0.7.0.dist-info/RECORD
