Metadata-Version: 2.1
Name: spora
Version: 0.7.0
Summary: spora: Streamlined Phylogenomic Outbreak Report Analysis
Home-page: https://github.com/matt-sd-watson/spora/
Author: Matthew Watson
Author-email: matthew.watson@oahpp.ca
License: UNKNOWN
Project-URL: Issues, https://github.com/matt-sd-watson/spora/issues
Project-URL: Source, https://github.com/matt-sd-watson/spora
Platform: UNKNOWN
Requires-Dist: pandas (>=1.1.5)
Requires-Dist: numpy (>=1.19)
Requires-Dist: biopython (>=1.79)
Requires-Dist: snakemake (>=7.0.0)
Requires-Dist: pypandoc (>=1.8)
Requires-Dist: pytest (>=7.1.2)
